{"models":[{"transform":[[1.0,0.0,0.0,0.0],[0.0,1.0,0.0,0.0],[0.0,0.0,1.0,0.0],[0.0,0.0,0.0,1.0]],"mobile":false,"foreground":false,"solid":true,"lights":[],"insert_colliders":"None","renderables":[],"components":[]},{"transform":[[1.0,0.0,0.0,0.0],[0.0,1.0,0.0,0.0],[0.0,0.0,1.0,0.0],[0.0,0.0,0.0,1.0]],"mobile":true,"foreground":false,"solid":false,"lights":[],"insert_colliders":{"Singular":{"collider":{"Cuboid":{"offset":[0.0,0.0,0.0],"half_extents":[0.25,0.25,0.25]}}}},"renderables":[{"Mesh":["cube",[[0.5,0.0,0.0,0.0],[0.0,0.5,0.0,0.0],[0.0,0.0,0.5,0.0],[0.0,0.0,0.0,1.0]],0]}],"components":[]},{"transform":[[2.500001,0.0,0.0,0.0],[0.0,2.0,0.0,0.0],[0.0,0.0,3.0,0.0],[-0.25,0.0,4.5,1.0]],"mobile":true,"foreground":false,"solid":true,"lights":[],"insert_colliders":"None","renderables":[{"Brush":["container",[0.0,0.0,0.0],[2.0,4.0,0.25],1]}],"components":[{"Door":{"radius":8.0,"height":3.75,"open_time":200}}]}],"brushes":[{"material":"watering","origin":[0.0,0.0,24.375],"extents":[14.5,10.0,2.25],"flags":1},{"material":"watering","origin":[0.0,4.5,7.125],"extents":[10.0,1.0,32.25],"flags":1},{"material":"watering","origin":[3.625,0.0,4.5],"extents":[2.75,8.0,2.5],"flags":1},{"material":"watering","origin":[0.0,-4.5,7.125],"extents":[10.0,1.0,32.25],"flags":1},{"material":"watering","origin":[-3.875,0.0,4.5],"extents":[2.25,8.0,2.5],"flags":1},{"material":"watering","origin":[-6.125,0.0,7.125],"extents":[2.25,10.0,32.25],"flags":1},{"material":"watering","origin":[6.125,0.0,19.625],"extents":[2.25,10.0,7.25],"flags":1},{"material":"watering","origin":[0.0,0.0,-10.125],"extents":[14.5,10.0,2.25],"flags":1},{"material":"slime","origin":[-0.25,-3.875,14.75],"extents":[3.0,0.25,3.0],"flags":1},{"material":"concrete","origin":[1.75,-3.875,14.75],"extents":[1.0,0.25,5.0],"flags":1},{"material":"concrete","origin":[-0.25,-3.875,12.75],"extents":[3.0,0.25,1.0],"flags":1},{"material":"concrete","origin":[-0.25,-3.875,16.75],"extents":[3.0,0.25,1.0],"flags":1},{"material":"concrete","origin":[-2.25,-3.875,14.75],"extents":[1.0,0.25,5.0],"flags":1},{"material":"watering","origin":[6.125,3.75,14.5],"extents":[2.25,2.5,3.0],"flags":1},{"material":"watering","origin":[6.125,0.0,2.0],"extents":[2.25,10.0,22.0],"flags":1},{"material":"watering","origin":[6.125,-2.75,14.5],"extents":[2.25,4.5,3.0],"flags":1},{"material":"concrete","origin":[13.5,1.0,12.625],"extents":[12.5,4.5,0.75],"flags":1},{"material":"concrete","origin":[4.5,-0.875,14.5],"extents":[1.0,0.75,3.0],"flags":1},{"material":"concrete","origin":[13.5,-0.875,14.5],"extents":[12.5,0.75,3.0],"flags":1},{"material":"concrete","origin":[13.5,2.875,14.5],"extents":[12.5,0.75,3.0],"flags":1},{"material":"concrete","origin":[13.5,1.0,16.375],"extents":[12.5,4.5,0.75],"flags":1}],"gravity":15.0,"air_friction":0.995,"materials":[{"name":"slime","diffuse":"slime","specular":"tar_specular","shininess":32.0,"physical_properties":{"friction":0.5,"control":0.2,"jump":2.0}},{"name":"default","diffuse":"magic_pixel","specular":"evil_pixel","shininess":32.0,"physical_properties":{"friction":0.8,"control":1.0,"jump":1.0}},{"name":"ice","diffuse":"ice","specular":"ice_specular","shininess":32.0,"physical_properties":{"friction":0.99,"control":0.05,"jump":1.0}},{"name":"evilwatering","diffuse":"evilwatering","specular":"evilwatering_specular","shininess":32.0,"physical_properties":{"friction":0.8,"control":1.0,"jump":1.0}},{"name":"end_sky","diffuse":"end_sky","specular":"end_sky_specular","shininess":32.0,"physical_properties":{"friction":0.8,"control":1.0,"jump":1.0}},{"name":"concrete","diffuse":"concrete","specular":"concrete_specular","shininess":32.0,"physical_properties":{"friction":0.8,"control":1.0,"jump":1.0}},{"name":"sparkle","diffuse":"sparkle","specular":"sparkle_specular","shininess":32.0,"physical_properties":{"friction":0.8,"control":1.0,"jump":1.0}},{"name":"tar","diffuse":"tar","specular":"tar_specular","shininess":32.0,"physical_properties":{"friction":0.25,"control":0.03,"jump":0.1}},{"name":"container","diffuse":"container","specular":"container_specular","shininess":32.0,"physical_properties":{"friction":0.8,"control":1.0,"jump":1.0}},{"name":"pillows_old_floor","diffuse":"pillows_old_floor","specular":"pillows_old_floor_specular","shininess":32.0,"physical_properties":{"friction":0.8,"control":1.0,"jump":1.0}},{"name":"sky","diffuse":"sky","specular":"sky_specular","shininess":32.0,"physical_properties":{"friction":0.8,"control":1.0,"jump":1.0}},{"name":"test","diffuse":"test","specular":"evil_pixel","shininess":32.0,"physical_properties":{"friction":0.8,"control":1.0,"jump":1.0}},{"name":"watering","diffuse":"watering","specular":"watering_specular","shininess":32.0,"physical_properties":{"friction":0.8,"control":1.0,"jump":1.0}}],"environment":{"skybox":{"Cubemap":"heaven"},"dir_light":{"direction":[-0.5497231,-0.6539521,0.51976067],"ambient":[0.325,0.3075,0.1675],"diffuse":[0.65,0.615,0.335],"specular":[0.325,0.3075,0.1675]}}}